giftparcelstruct/__init__.py
giftparcelstruct/main.py
giftparcelstruct/prompts.py
giftparcelstruct-2025.12.21101054.dist-info/METADATA
giftparcelstruct-2025.12.21101054.dist-info/WHEEL
giftparcelstruct-2025.12.21101054.dist-info/top_level.txt
giftparcelstruct-2025.12.21101054.dist-info/RECORD
