Metadata-Version: 2.4
Name: giftparcelstruct
Version: 2025.12.21101054
Summary: A new package that processes user-submitted text descriptions of gift-wrapped parcels and returns a structured analysis of the contents, wrapping quality, and potential surprises. It uses pattern matc
Author-email: giftparcelstruct <hi@eugene.plus>
License: MIT
Project-URL: Homepage, https://github.com/chigwell/giftparcelstruct
Requires-Python: >=3.9
Requires-Dist: langchain-llm7>=0.0.0
Requires-Dist: llmatch-messages>=0.0.0
Requires-Dist: langchain-core>=0.3.0
